jeepney-stubs/__init__.pyi
jeepney-stubs/auth.pyi
jeepney-stubs/bindgen.pyi
jeepney-stubs/bus.pyi
jeepney-stubs/bus_messages.pyi
jeepney-stubs/fds.pyi
jeepney-stubs/io/__init__.pyi
jeepney-stubs/io/asyncio.pyi
jeepney-stubs/io/blocking.pyi
jeepney-stubs/io/common.pyi
jeepney-stubs/io/threading.pyi
jeepney-stubs/io/trio.pyi
jeepney-stubs/low_level.pyi
jeepney-stubs/wrappers.pyi
jeepney_stubs-0.1.0.dist-info/WHEEL
jeepney_stubs-0.1.0.dist-info/METADATA
jeepney_stubs-0.1.0.dist-info/RECORD
