Metadata-Version: 2.3
Name: jeepney-stubs
Version: 0.1.0
Summary: Type stubs for jeepney
